ocfagent/__init__.py
ocfagent/agent.py
ocfagent/error.py
ocfagent/parameter.py
pyocfagent-0.12.dist-info/DESCRIPTION.rst
pyocfagent-0.12.dist-info/METADATA
pyocfagent-0.12.dist-info/RECORD
pyocfagent-0.12.dist-info/WHEEL
pyocfagent-0.12.dist-info/metadata.json
pyocfagent-0.12.dist-info/top_level.txt
