Metadata-Version: 2.0
Name: pyocfagent
Version: 0.12
Summary: Python OCF Resource Agent Framework for Pacemaker Clusters
Home-page: https://github.com/CygnusNetworks/pyocfagent
Author: Dr. Torge Szczepanek
Author-email: info@cygnusnetworks.de
License: GPLv2
Download-URL: https://github.com/CygnusNetworks/pyocfagent/tarball/v0.12
Keywords: pacemaker,ocf,agent,python
Platform: POSIX
Classifier: License :: OSI Approved :: GNU General Public License v2 (GPLv2)
Classifier: Programming Language :: Python
Classifier: Programming Language :: Python :: 2.7
Classifier: Development Status :: 5 - Production/Stable
Classifier: Operating System :: POSIX
Classifier: Topic :: Internet
Classifier: Topic :: System :: Networking
Requires-Dist: lxml
